jmdictpy/__init__.py
jmdictpy/api.py
jmdictpy/config.py
jmdictpy/database.py
jmdictpy/downloader.py
jmdictpy/models.py
jmdictpy/version.py
jmdictpy-0.1.1.dist-info/METADATA
jmdictpy-0.1.1.dist-info/WHEEL
jmdictpy-0.1.1.dist-info/licenses/LICENSE
jmdictpy-0.1.1.dist-info/RECORD
