Metadata-Version: 2.4
Name: jmdictpy
Version: 0.1.1
Summary: Fast Python wrapper for JMdict with SQLite backend and automatic updates
Author: JMdictPy Contributors
License: MIT
License-File: LICENSE
Keywords: dictionary,japanese,jmdict,jmnedict,kanjidic
Classifier: Development Status :: 4 - Beta
Classifier: Intended Audience :: Developers
Classifier: License :: OSI Approved :: MIT License
Classifier: Programming Language :: Python :: 3
Classifier: Programming Language :: Python :: 3.10
Classifier: Programming Language :: Python :: 3.11
Classifier: Programming Language :: Python :: 3.12
Classifier: Topic :: Text Processing :: Linguistic
Requires-Python: >=3.10
Requires-Dist: requests>=2.25.0
Provides-Extra: dev
Requires-Dist: pytest>=7.0.0; extra == 'dev'
